arxiv_export_documents/__init__.py
arxiv_export_documents/arxiv_data.py
arxiv_export_documents/arxiv_export.py
arxiv_export_documents-0.1.8.dist-info/licenses/LICENSE.md
arxiv_export_documents-0.1.8.dist-info/METADATA
arxiv_export_documents-0.1.8.dist-info/WHEEL
arxiv_export_documents-0.1.8.dist-info/top_level.txt
arxiv_export_documents-0.1.8.dist-info/RECORD
